dagster_airbyte/__init__.py
dagster_airbyte/asset_defs.py
dagster_airbyte/ops.py
dagster_airbyte/resources.py
dagster_airbyte/types.py
dagster_airbyte/utils.py
dagster_airbyte/version.py
dagster_airbyte-1.0.5.dist-info/LICENSE
dagster_airbyte-1.0.5.dist-info/METADATA
dagster_airbyte-1.0.5.dist-info/WHEEL
dagster_airbyte-1.0.5.dist-info/top_level.txt
dagster_airbyte-1.0.5.dist-info/RECORD
